{"courses":
        [
            {"id": "111111",
              "current_location": {"lat": 32.069235, "lon": 34.825947},
            "source": {"lat": 32.069235, "lon": 34.825947, "name": "Shlomtsiyon 13-1 Ramat Gan"},
            "destination": {"lat": 0, "lon": 0, "name": "Rokach Boulevard, Tel Aviv-Yafo"}},
            {"id": "222222",
              "current_location": {"lat": 32.069235, "lon": 34.825947},
            "source": {"lat": 0, "lon": 0, "name": "Shlomtsiyon 13-1 Ramat Gan"},
            "destination": {"lat": 0, "lon": 0, "name": "Tagore St 55 Tel Aviv"}}
        ]
}